{
    "task" : {
        "task_vars" : {
            "left_blue" : true,
            "response_window"  : 2000
        },
        "settings" : {
            "release_timeout"  : 3000,
            "invalid_button"   : "You have pressed an invalid button.",
            "too_slow"         : "Please try to respond faster.",
            "release_buttons"  : "You only need to press the buttons very shortly; you can let go of the buttons."
        }
    },
    "blocks" : [
        {
            "intro_slides" : [
                "In a moment you will see a couple of pictures.",
                "If the picture shows a burger, then Press D. If the picture shows a salad, then press K."
            ],
            "block_vars" : {
                "name" : "prac"
            },
            "trials" : [
                { "stim" : "burger"  },
                { "stim" : "salad"   }                
            ]
        }, {
            "intro_slides" : [
                "This is the main block"
            ],
            "block_vars" : {
                "name" : "main"
            },
            "trials" : [
                { "stim" : "burger"  },
                { "stim" : "salad"   }
            ]
        }
    ],
    "slideshow" : {
        "buttons" : {
            "vmouseup" : {
                "type"    : "specific",
                "buttons" : {
                    "#touch_left"  : "previous",
                    "#touch_right" : "next"
                }
            },
            "keyup" : {
                "type"    : "specific",
                "buttons" : {
                    "68" : "previous",  
                    "75" : "next"  
                }
            } 
        },
        "button_texts" : {
            "first"  : "Press K to continue",
            "middle" : "Press K to continue; press D to go back",
            "last"   : "Press K to continue; press D to go back"
        },
        "button_delay" : 0,
        "container_id" : "#instruction_container",
        "text_id"      : "#instruction_text"
    },
    "task_buttons" : {
        "down" : {
            "vmousedown" : {
                "type"    : "all",
                "buttons" : {
                    "#touch_left"  : "left",
                    "#touch_right" : "right"
                }
            },
            "keydown" : {
                "type"    : "all",
                "buttons" : {
                    "68" : "left",  
                    "75" : "right"  
                }
            } 
        },
        "up" : {
            "vmouseup" : {
                "type"    : "specific",
                "buttons" : {
                    "#touch_left"  : "left",
                    "#touch_right" : "right"
                }
            },
            "keyup" : {
                "type"    : "specific",
                "buttons" : {
                    "68" : "left",  
                    "75" : "right"  
                }
            } 
        }       
    }
}
